trx/__init__.py
trx/fetcher.py
trx/io.py
trx/streamlines_ops.py
trx/trx_file_memmap.py
trx/utils.py
trx/version.py
trx/viz.py
trx/workflows.py
trx/tests/test_io.py
trx/tests/test_memmap.py
trx/tests/test_streamlines_ops.py
trx_python-0.2.9.data/scripts/tff_concatenate_tractograms.py
trx_python-0.2.9.data/scripts/tff_convert_dsi_studio.py
trx_python-0.2.9.data/scripts/tff_convert_tractogram.py
trx_python-0.2.9.data/scripts/tff_generate_trx_from_scratch.py
trx_python-0.2.9.data/scripts/tff_manipulate_datatype.py
trx_python-0.2.9.data/scripts/tff_simple_compare.py
trx_python-0.2.9.data/scripts/tff_validate_trx.py
trx_python-0.2.9.data/scripts/tff_verify_header_compatibility.py
trx_python-0.2.9.data/scripts/tff_visualize_overlap.py
trx_python-0.2.9.dist-info/LICENSE
trx_python-0.2.9.dist-info/METADATA
trx_python-0.2.9.dist-info/WHEEL
trx_python-0.2.9.dist-info/top_level.txt
trx_python-0.2.9.dist-info/RECORD
