Metadata-Version: 2.1
Name: trx-python
Version: 0.2.9
Summary: Experiments with new file format for tractography
Home-page: https://github.com/tee-ar-ex/trx-python
License: BSD License
Platform: OS Independent
Classifier: Development Status :: 3 - Alpha
Classifier: Environment :: Console
Classifier: Intended Audience :: Science/Research
Classifier: License :: OSI Approved :: BSD License
Classifier: Operating System :: OS Independent
Classifier: Programming Language :: Python
Classifier: Topic :: Scientific/Engineering
Requires-Python: >=3.8
License-File: LICENSE
Requires-Dist: setuptools-scm
Requires-Dist: deepdiff
Requires-Dist: nibabel >=5
Requires-Dist: numpy >=1.22
Provides-Extra: all
Requires-Dist: astroid ==2.15.8 ; extra == 'all'
Requires-Dist: sphinx ; extra == 'all'
Requires-Dist: pydata-sphinx-theme ; extra == 'all'
Requires-Dist: sphinx-autoapi ; extra == 'all'
Requires-Dist: numpydoc ; extra == 'all'
Requires-Dist: flake8 ; extra == 'all'
Requires-Dist: psutil ; extra == 'all'
Requires-Dist: pytest >=7 ; extra == 'all'
Requires-Dist: pytest-console-scripts >=0 ; extra == 'all'
Provides-Extra: doc
Requires-Dist: astroid ==2.15.8 ; extra == 'doc'
Requires-Dist: sphinx ; extra == 'doc'
Requires-Dist: pydata-sphinx-theme ; extra == 'doc'
Requires-Dist: sphinx-autoapi ; extra == 'doc'
Requires-Dist: numpydoc ; extra == 'doc'
Provides-Extra: test
Requires-Dist: flake8 ; extra == 'test'
Requires-Dist: psutil ; extra == 'test'
Requires-Dist: pytest >=7 ; extra == 'test'
Requires-Dist: pytest-console-scripts >=0 ; extra == 'test'
